LICENSE.md
MANIFEST.in
README.md
pyproject.toml
setup.cfg
setup.py
afwizard/__init__.py
afwizard/__main__.py
afwizard/apps.py
afwizard/asprs.py
afwizard/dataset.py
afwizard/execute.py
afwizard/filter.py
afwizard/lastools.py
afwizard/library.py
afwizard/logger.py
afwizard/opals.py
afwizard/paths.py
afwizard/pdal.py
afwizard/segmentation.py
afwizard/utils.py
afwizard/versioning.py
afwizard/visualization.py
afwizard/widgets.py
afwizard.egg-info/PKG-INFO
afwizard.egg-info/SOURCES.txt
afwizard.egg-info/dependency_links.txt
afwizard.egg-info/entry_points.txt
afwizard.egg-info/requires.txt
afwizard.egg-info/top_level.txt
afwizard/jupyter/datasets.ipynb
afwizard/jupyter/filtering.ipynb
afwizard/jupyter/libraries.ipynb
afwizard/jupyter/python.ipynb
afwizard/jupyter/segmentation.ipynb
afwizard/jupyter/selection.ipynb
afwizard/schema/filter.json
afwizard/schema/lastools.json
afwizard/schema/library.json
afwizard/schema/opals.json
afwizard/schema/pdal.json
afwizard/schema/pipeline.json
afwizard/schema/rasterize.json
afwizard/schema/segment_metadata.json
afwizard/schema/variability.json
afwizard/schema/visualization.json
tests/__init__.py
tests/conftest.py
tests/test_apps.py
tests/test_asprs.py
tests/test_cli.py
tests/test_dataset.py
tests/test_execute.py
tests/test_filter.py
tests/test_lastools.py
tests/test_library.py
tests/test_opals.py
tests/test_paths.py
tests/test_pdal.py
tests/test_segmentation.py
tests/test_version.py
tests/test_widgets.py