Metadata-Version: 2.4
Name: afwizard
Version: 1.0.1
Summary: Adaptive Filtering Wizard
Author: Dominic Kempf
Author-email: ssc@iwr.uni-heidelberg.de
License: MIT
Classifier: Operating System :: OS Independent
Classifier: Programming Language :: Python :: 3
License-File: LICENSE.md
Requires-Dist: Click
Requires-Dist: IPython
Requires-Dist: afwizard-library
Requires-Dist: gdal==3.4.0
Requires-Dist: geojson
Requires-Dist: ipyfilechooser
Requires-Dist: ipyleaflet
Requires-Dist: ipywidgets>=8
Requires-Dist: ipywidgets-jsonschema
Requires-Dist: jsonmerge
Requires-Dist: jsonschema<4
Requires-Dist: numpy
Requires-Dist: pdal
Requires-Dist: pillow
Requires-Dist: pooch
Requires-Dist: pyproj
Requires-Dist: pyrsistent
Requires-Dist: pytools
Requires-Dist: wrapt
Requires-Dist: xdg
Requires-Dist: xmltodict
Dynamic: license-file
